.coveragerc
.gitignore
AUTHORS.rst
CHANGELOG.rst
LICENSE
LICENSE.txt
Pipfile
Pipfile.lock
README.md
README.rst
requirements.txt
setup.cfg
setup.py
.vscode/launch.json
docs/Makefile
docs/authors.rst
docs/changelog.rst
docs/conf.py
docs/index.rst
docs/license.rst
docs/_static/.gitignore
src/croudtech_cloudformation/__init__.py
src/croudtech_cloudformation/cli.py
src/croudtech_cloudformation/cloudformation.py
src/croudtech_cloudformation.egg-info/PKG-INFO
src/croudtech_cloudformation.egg-info/SOURCES.txt
src/croudtech_cloudformation.egg-info/dependency_links.txt
src/croudtech_cloudformation.egg-info/entry_points.txt
src/croudtech_cloudformation.egg-info/not-zip-safe
src/croudtech_cloudformation.egg-info/requires.txt
src/croudtech_cloudformation.egg-info/top_level.txt
tests/conftest.py
tests/test_dummy.py
tests/test_skeleton.py