Metadata-Version: 2.1
Name: croudtech-cloudformation
Version: 1.0.2
Summary: Add a short description here!
Home-page: https://github.com/pyscaffold/pyscaffold/
Author: Jim Robinson
Author-email: jscrobinson@gmail.com
License: mit
Project-URL: Documentation, https://pyscaffold.org/
Platform: any
Classifier: Development Status :: 4 - Beta
Classifier: Programming Language :: Python
